{
	"setId": 100,
	"decks": [
		{
			"deckId": 101,
			"setId": 100,
			"deckImage": "sets/core/profilepics/captain-america.jpg",
			"deckName": "Captain America",
			"deckType": "Heroes",
			"cards": [
				{
					"deckId": 101,
					"setId": 100,
					"cardImage": "sets/core/heroes/captain-america-01.jpg",
					"cardType": "Hero-Rare",
					"teamName": "Avengers",
					"cardName": "A Day Unlike Any Other"
				},
				{
					"deckId": 101,
					"setId": 100,
					"cardImage": "sets/core/heroes/captain-america-02.jpg",
					"cardType": "Hero-Uncommon",
					"teamName": "Avengers",
					"cardName": "Diving Block"
				},
				{
					"deckId": 101,
					"setId": 100,
					"cardImage": "sets/core/heroes/captain-america-03.jpg",
					"cardType": "Hero-Common",
					"teamName": "Avengers",
					"cardName": "Perfect Teamwork"
				},
				{
					"deckId": 101,
					"setId": 100,
					"cardImage": "sets/core/heroes/captain-america-04.jpg",
					"cardType": "Hero-Common",
					"teamName": "Avengers",
					"cardName": "Avengers Assemble!"
				}
			]
		},
		{
			"deckId": 102,
			"setId": 100,
			"deckImage": "sets/core/profilepics/iron-man.jpg",
			"deckName": "Iron Man",
			"deckType": "Heroes",
			"cards": [
				{
					"deckId": 102,
					"setId": 100,
					"cardImage": "sets/core/heroes/iron-man-01.jpg",
					"cardType": "Hero-Rare",
					"teamName": "Avengers",
					"cardName": "-"
				},
				{
					"deckId": 102,
					"setId": 100,
					"cardImage": "sets/core/heroes/iron-man-02.jpg",
					"cardType": "Hero-Uncommon",
					"teamName": "Avengers",
					"cardName": "-"
				},
				{
					"deckId": 102,
					"setId": 100,
					"cardImage": "sets/core/heroes/iron-man-03.jpg",
					"cardType": "Hero-Common",
					"teamName": "Avengers",
					"cardName": "-"
				},
				{
					"deckId": 102,
					"setId": 100,
					"cardImage": "sets/core/heroes/iron-man-04.jpg",
					"cardType": "Hero-Common",
					"teamName": "Avengers",
					"cardName": "-"
				}
			]
		},
		{
			"deckId": 103,
			"setId": 100,
			"deckImage": "sets/core/profilepics/black-widow.jpg",
			"deckName": "Black Widow",
			"deckType": "Heroes",
			"cards": [
				{
					"deckId": 103,
					"setId": 100,
					"cardImage": "sets/core/heroes/black-widow-01.jpg",
					"cardType": "Hero-Rare",
					"teamName": "Avengers",
					"cardName": "-"
				},
				{
					"deckId": 103,
					"setId": 100,
					"cardImage": "sets/core/heroes/black-widow-02.jpg",
					"cardType": "Hero-Uncommon",
					"teamName": "Avengers",
					"cardName": "-"
				},
				{
					"deckId": 103,
					"setId": 100,
					"cardImage": "sets/core/heroes/black-widow-03.jpg",
					"cardType": "Hero-Common",
					"teamName": "Avengers",
					"cardName": "-"
				},
				{
					"deckId": 103,
					"setId": 100,
					"cardImage": "sets/core/heroes/black-widow-04.jpg",
					"cardType": "Hero-Common",
					"teamName": "Avengers",
					"cardName": "-"
				}
			]
		},
		{
			"deckId": 104,
			"setId": 100,
			"deckImage": "sets/core/profilepics/hawkeye.jpg",
			"deckName": "Hawkeye",
			"deckType": "Heroes",
			"cards": [
				{
					"deckId": 104,
					"setId": 100,
					"cardImage": "sets/core/heroes/hawkeye-01.jpg",
					"cardType": "Hero-Rare",
					"teamName": "Avengers",
					"cardName": "-"
				},
				{
					"deckId": 104,
					"setId": 100,
					"cardImage": "sets/core/heroes/hawkeye-02.jpg",
					"cardType": "Hero-Uncommon",
					"teamName": "Avengers",
					"cardName": "-"
				},
				{
					"deckId": 104,
					"setId": 100,
					"cardImage": "sets/core/heroes/hawkeye-03.jpg",
					"cardType": "Hero-Common",
					"teamName": "Avengers",
					"cardName": "-"
				},
				{
					"deckId": 104,
					"setId": 100,
					"cardImage": "sets/core/heroes/hawkeye-04.jpg",
					"cardType": "Hero-Common",
					"teamName": "Avengers",
					"cardName": "-"
				}
			]
		},
		{
			"deckId": 105,
			"setId": 100,
			"deckImage": "sets/core/profilepics/cyclops.jpg",
			"deckName": "Cyclops",
			"deckType": "Heroes",
			"cards": [
				{
					"deckId": 105,
					"setId": 100,
					"cardImage": "sets/core/heroes/cyclops-01.jpg",
					"cardType": "Hero-Rare",
					"teamName": "X-Men",
					"cardName": "-"
				},
				{
					"deckId": 105,
					"setId": 100,
					"cardImage": "sets/core/heroes/cyclops-02.jpg",
					"cardType": "Hero-Uncommon",
					"teamName": "X-Men",
					"cardName": "-"
				},
				{
					"deckId": 105,
					"setId": 100,
					"cardImage": "sets/core/heroes/cyclops-03.jpg",
					"cardType": "Hero-Common",
					"teamName": "X-Men",
					"cardName": "-"
				},
				{
					"deckId": 105,
					"setId": 100,
					"cardImage": "sets/core/heroes/cyclops-04.jpg",
					"cardType": "Hero-Common",
					"teamName": "X-Men",
					"cardName": "-"
				}
			]
		},
		{
			"deckId": 106,
			"setId": 100,
			"deckImage": "sets/core/profilepics/deadpool.jpg",
			"deckName": "Deadpool",
			"deckType": "Heroes",
			"cards": [
				{
					"deckId": 106,
					"setId": 100,
					"cardImage": "sets/core/heroes/deadpool-01.jpg",
					"cardType": "Hero-Rare",
					"teamName": "Mercs For Money",
					"cardName": "-"
				},
				{
					"deckId": 106,
					"setId": 100,
					"cardImage": "sets/core/heroes/deadpool-02.jpg",
					"cardType": "Hero-Uncommon",
					"teamName": "Mercs For Money",
					"cardName": "-"
				},
				{
					"deckId": 106,
					"setId": 100,
					"cardImage": "sets/core/heroes/deadpool-03.jpg",
					"cardType": "Hero-Common",
					"teamName": "Mercs For Money",
					"cardName": "-"
				},
				{
					"deckId": 106,
					"setId": 100,
					"cardImage": "sets/core/heroes/deadpool-04.jpg",
					"cardType": "Hero-Common",
					"teamName": "Mercs For Money",
					"cardName": "-"
				}
			]
		},
		{
			"deckId": 107,
			"setId": 100,
			"deckImage": "sets/core/profilepics/emma-frost.jpg",
			"deckName": "Emma Frost",
			"deckType": "Heroes",
			"cards": [
				{
					"deckId": 107,
					"setId": 100,
					"cardImage": "sets/core/heroes/emma-frost-01.jpg",
					"cardType": "Hero-Rare",
					"teamName": "X-Men",
					"cardName": "-"
				},
				{
					"deckId": 107,
					"setId": 100,
					"cardImage": "sets/core/heroes/emma-frost-02.jpg",
					"cardType": "Hero-Uncommon",
					"teamName": "X-Men",
					"cardName": "-"
				},
				{
					"deckId": 107,
					"setId": 100,
					"cardImage": "sets/core/heroes/emma-frost-03.jpg",
					"cardType": "Hero-Common",
					"teamName": "X-Men",
					"cardName": "-"
				},
				{
					"deckId": 107,
					"setId": 100,
					"cardImage": "sets/core/heroes/emma-frost-04.jpg",
					"cardType": "Hero-Common",
					"teamName": "X-Men",
					"cardName": "-"
				}
			]
		},
		{
			"deckId": 108,
			"setId": 100,
			"deckImage": "sets/core/profilepics/gambit.jpg",
			"deckName": "Gambit",
			"deckType": "Heroes",
			"cards": [
				{
					"deckId": 108,
					"setId": 100,
					"cardImage": "sets/core/heroes/gambit-01.jpg",
					"cardType": "Hero-Rare",
					"teamName": "X-Men",
					"cardName": "-"
				},
				{
					"deckId": 108,
					"setId": 100,
					"cardImage": "sets/core/heroes/gambit-02.jpg",
					"cardType": "Hero-Uncommon",
					"teamName": "X-Men",
					"cardName": "-"
				},
				{
					"deckId": 108,
					"setId": 100,
					"cardImage": "sets/core/heroes/gambit-03.jpg",
					"cardType": "Hero-Common",
					"teamName": "X-Men",
					"cardName": "-"
				},
				{
					"deckId": 108,
					"setId": 100,
					"cardImage": "sets/core/heroes/gambit-04.jpg",
					"cardType": "Hero-Common",
					"teamName": "X-Men",
					"cardName": "-"
				}
			]
		},
		{
			"deckId": 109,
			"setId": 100,
			"deckImage": "sets/core/profilepics/hulk.jpg",
			"deckName": "Hulk",
			"deckType": "Heroes",
			"cards": [
				{
					"deckId": 109,
					"setId": 100,
					"cardImage": "sets/core/heroes/hulk-01.jpg",
					"cardType": "Hero-Rare",
					"teamName": "Avengers",
					"cardName": "-"
				},
				{
					"deckId": 109,
					"setId": 100,
					"cardImage": "sets/core/heroes/hulk-02.jpg",
					"cardType": "Hero-Uncommon",
					"teamName": "Avengers",
					"cardName": "-"
				},
				{
					"deckId": 109,
					"setId": 100,
					"cardImage": "sets/core/heroes/hulk-03.jpg",
					"cardType": "Hero-Common",
					"teamName": "Avengers",
					"cardName": "-"
				},
				{
					"deckId": 109,
					"setId": 100,
					"cardImage": "sets/core/heroes/hulk-04.jpg",
					"cardType": "Hero-Common",
					"teamName": "Avengers",
					"cardName": "-"
				}
			]
		},
		{
			"deckId": 110,
			"setId": 100,
			"deckImage": "sets/core/profilepics/nick-fury.jpg",
			"deckName": "Nick Fury",
			"deckType": "Heroes",
			"cards": [
				{
					"deckId": 110,
					"setId": 100,
					"cardImage": "sets/core/heroes/nick-fury-01.jpg",
					"cardType": "Hero-Rare",
					"teamName": "S.H.I.E.L.D.",
					"cardName": "-"
				},
				{
					"deckId": 110,
					"setId": 100,
					"cardImage": "sets/core/heroes/nick-fury-02.jpg",
					"cardType": "Hero-Uncommon",
					"teamName": "S.H.I.E.L.D.",
					"cardName": "-"
				},
				{
					"deckId": 110,
					"setId": 100,
					"cardImage": "sets/core/heroes/nick-fury-03.jpg",
					"cardType": "Hero-Common",
					"teamName": "S.H.I.E.L.D.",
					"cardName": "-"
				},
				{
					"deckId": 110,
					"setId": 100,
					"cardImage": "sets/core/heroes/nick-fury-04.jpg",
					"cardType": "Hero-Common",
					"teamName": "S.H.I.E.L.D.",
					"cardName": "-"
				}
			]
		},
		{
			"deckId": 111,
			"setId": 100,
			"deckImage": "sets/core/profilepics/rogue.jpg",
			"deckName": "Rogue",
			"deckType": "Heroes",
			"cards": [
				{
					"deckId": 111,
					"setId": 100,
					"cardImage": "sets/core/heroes/rogue-01.jpg",
					"cardType": "Hero-Rare",
					"teamName": "X-Men",
					"cardName": "-"
				},
				{
					"deckId": 111,
					"setId": 100,
					"cardImage": "sets/core/heroes/rogue-02.jpg",
					"cardType": "Hero-Uncommon",
					"teamName": "X-Men",
					"cardName": "-"
				},
				{
					"deckId": 111,
					"setId": 100,
					"cardImage": "sets/core/heroes/rogue-03.jpg",
					"cardType": "Hero-Common",
					"teamName": "X-Men",
					"cardName": "-"
				},
				{
					"deckId": 111,
					"setId": 100,
					"cardImage": "sets/core/heroes/rogue-04.jpg",
					"cardType": "Hero-Common",
					"teamName": "X-Men",
					"cardName": "-"
				}
			]
		},
		{
			"deckId": 112,
			"setId": 100,
			"deckImage": "sets/core/profilepics/spider-man.jpg",
			"deckName": "Spider-Man",
			"deckType": "Heroes",
			"cards": [
				{
					"deckId": 112,
					"setId": 100,
					"cardImage": "sets/core/heroes/spider-man-01.jpg",
					"cardType": "Hero-Rare",
					"teamName": "Spider-Friends",
					"cardName": "-"
				},
				{
					"deckId": 112,
					"setId": 100,
					"cardImage": "sets/core/heroes/spider-man-02.jpg",
					"cardType": "Hero-Uncommon",
					"teamName": "Spider-Friends",
					"cardName": "-"
				},
				{
					"deckId": 112,
					"setId": 100,
					"cardImage": "sets/core/heroes/spider-man-03.jpg",
					"cardType": "Hero-Common",
					"teamName": "Spider-Friends",
					"cardName": "-"
				},
				{
					"deckId": 112,
					"setId": 100,
					"cardImage": "sets/core/heroes/spider-man-04.jpg",
					"cardType": "Hero-Common",
					"teamName": "Spider-Friends",
					"cardName": "-"
				}
			]
		},
		{
			"deckId": 113,
			"setId": 100,
			"deckImage": "sets/core/profilepics/thor.jpg",
			"deckName": "Thor",
			"deckType": "Heroes",
			"cards": [
				{
					"deckId": 113,
					"setId": 100,
					"cardImage": "sets/core/heroes/thor-01.jpg",
					"cardType": "Hero-Rare",
					"teamName": "Avengers",
					"cardName": "-"
				},
				{
					"deckId": 113,
					"setId": 100,
					"cardImage": "sets/core/heroes/thor-02.jpg",
					"cardType": "Hero-Uncommon",
					"teamName": "Avengers",
					"cardName": "-"
				},
				{
					"deckId": 113,
					"setId": 100,
					"cardImage": "sets/core/heroes/thor-03.jpg",
					"cardType": "Hero-Common",
					"teamName": "Avengers",
					"cardName": "-"
				},
				{
					"deckId": 113,
					"setId": 100,
					"cardImage": "sets/core/heroes/thor-04.jpg",
					"cardType": "Hero-Common",
					"teamName": "Avengers",
					"cardName": "-"
				}
			]
		},
		{
			"deckId": 114,
			"setId": 100,
			"deckImage": "sets/core/profilepics/wolverine.jpg",
			"deckName": "Wolverine",
			"deckType": "Heroes",
			"cards": [
				{
					"deckId": 114,
					"setId": 100,
					"cardImage": "sets/core/heroes/wolverine-01.jpg",
					"cardType": "Hero-Rare",
					"teamName": "X-Men",
					"cardName": "-"
				},
				{
					"deckId": 114,
					"setId": 100,
					"cardImage": "sets/core/heroes/wolverine-02.jpg",
					"cardType": "Hero-Uncommon",
					"teamName": "X-Men",
					"cardName": "-"
				},
				{
					"deckId": 114,
					"setId": 100,
					"cardImage": "sets/core/heroes/wolverine-03.jpg",
					"cardType": "Hero-Common",
					"teamName": "X-Men",
					"cardName": "-"
				},
				{
					"deckId": 114,
					"setId": 100,
					"cardImage": "sets/core/heroes/wolverine-04.jpg",
					"cardType": "Hero-Common",
					"teamName": "X-Men",
					"cardName": "-"
				}
			]
		},
		{
			"deckId": 115,
			"setId": 100,
			"deckImage": "sets/core/profilepics/dr-doom.png",
			"deckName": "Dr. Doom",
			"deckType": "Masterminds",
			"cards": [
				{
					"deckId": 115,
					"setId": 100,
					"cardImage": "sets/core/masterminds/dr-doom-01.jpg",
					"cardType": "Mastermind",
					"teamName": "Dr. Doom",
					"cardName": "-"
				},
				{
					"deckId": 115,
					"setId": 100,
					"cardImage": "sets/core/masterminds/dr-doom-02.jpg",
					"cardType": "Mastermind Tactic",
					"teamName": "Dr. Doom",
					"cardName": "-"
				},
				{
					"deckId": 115,
					"setId": 100,
					"cardImage": "sets/core/masterminds/dr-doom-03.jpg",
					"cardType": "Mastermind Tactic",
					"teamName": "Dr. Doom",
					"cardName": "-"
				},
				{
					"deckId": 115,
					"setId": 100,
					"cardImage": "sets/core/masterminds/dr-doom-04.jpg",
					"cardType": "Mastermind Tactic",
					"teamName": "Dr. Doom",
					"cardName": "-"
				},
				{
					"deckId": 115,
					"setId": 100,
					"cardImage": "sets/core/masterminds/dr-doom-05.jpg",
					"cardType": "Mastermind Tactic",
					"teamName": "Dr. Doom",
					"cardName": "-"
				}
			]
		},
		{
			"deckId": 116,
			"setId": 100,
			"deckImage": "sets/core/profilepics/loki.png",
			"deckName": "Loki",
			"deckType": "Masterminds",
			"cards": [
				{
					"deckId": 116,
					"setId": 100,
					"cardImage": "sets/core/masterminds/loki-01.jpg",
					"cardType": "Mastermind",
					"teamName": "Foes Of Asgard",
					"cardName": "-"
				},
				{
					"deckId": 116,
					"setId": 100,
					"cardImage": "sets/core/masterminds/loki-02.jpg",
					"cardType": "Mastermind Tactic",
					"teamName": "Foes Of Asgard",
					"cardName": "-"
				},
				{
					"deckId": 116,
					"setId": 100,
					"cardImage": "sets/core/masterminds/loki-03.jpg",
					"cardType": "Mastermind Tactic",
					"teamName": "Foes Of Asgard",
					"cardName": ""
				},
				{
					"deckId": 116,
					"setId": 116,
					"cardImage": "sets/core/masterminds/loki-04.jpg",
					"cardType": "Mastermind Tactic",
					"teamName": "Foes Of Asgard",
					"cardName": "-"
				},
				{
					"deckId": 116,
					"setId": 100,
					"cardImage": "sets/core/masterminds/loki-05.jpg",
					"cardType": "Mastermind Tactic",
					"teamName": "Foes Of Asgard",
					"cardName": "-"
				}
			]
		},
		{
			"deckId": 117,
			"setId": 100,
			"deckImage": "sets/core/profilepics/magneto.png",
			"deckName": "Magneto",
			"deckType": "Masterminds",
			"cards": [
				{
					"deckId": 117,
					"setId": 100,
					"cardImage": "sets/core/masterminds/magneto-01.jpg",
					"cardType": "Mastermind",
					"teamName": "Brotherhood",
					"cardName": "-"
				},
				{
					"deckId": 117,
					"setId": 100,
					"cardImage": "sets/core/masterminds/magneto-02.jpg",
					"cardType": "Mastermind Tactic",
					"teamName": "Brotherhood",
					"cardName": "-"
				},
				{
					"deckId": 117,
					"setId": 100,
					"cardImage": "sets/core/masterminds/magneto-03.jpg",
					"cardType": "Mastermind Tactic",
					"teamName": "Brotherhood",
					"cardName": "-"
				},
				{
					"deckId": 117,
					"setId": 100,
					"cardImage": "sets/core/masterminds/magneto-04.jpg",
					"cardType": "Mastermind Tactic",
					"teamName": "Brotherhood",
					"cardName": "-"
				},
				{
					"deckId": 117,
					"setId": 100,
					"cardImage": "sets/core/masterminds/magneto-05.jpg",
					"cardType": "Mastermind Tactic",
					"teamName": "Brotherhood",
					"cardName": "-"
				}
			]
		},
		{
			"deckId": 118,
			"setId": 100,
			"deckImage": "sets/core/profilepics/red-skull.png",
			"deckName": "Red Skull",
			"deckType": "Masterminds",
			"cards": [
				{
					"deckId": 118,
					"setId": 100,
					"cardImage": "sets/core/masterminds/red-skull-01.jpg",
					"cardType": "Mastermind",
					"teamName": "HYDRA",
					"cardName": "-"
				},
				{
					"deckId": 118,
					"setId": 100,
					"cardImage": "sets/core/masterminds/red-skull-02.jpg",
					"cardType": "Mastermind Tactic",
					"teamName": "HYDRA",
					"cardName": "-"
				},
				{
					"deckId": 118,
					"setId": 100,
					"cardImage": "sets/core/masterminds/red-skull-03.jpg",
					"cardType": "Mastermind Tactic",
					"teamName": "HYDRA",
					"cardName": "-"
				},
				{
					"deckId": 118,
					"setId": 100,
					"cardImage": "sets/core/masterminds/red-skull-04.jpg",
					"cardType": "Mastermind Tactic",
					"teamName": "HYDRA",
					"cardName": "-"
				},
				{
					"deckId": 118,
					"setId": 100,
					"cardImage": "sets/core/masterminds/red-skull-05.jpg",
					"cardType": "Mastermind Tactic",
					"teamName": "HYDRA",
					"cardName": "-"
				}
			]
		},
		{
			"deckId": 119,
			"setId": 100,
			"deckImage": "sets/core/villains/hydra-01.jpg",
			"deckName": "HYDRA",
			"deckType": "Villains",
			"cards": [
				{
					"deckId": 119,
					"setId": 100,
					"cardImage": "sets/core/villains/hydra-01.jpg",
					"cardType": "Villain",
					"teamName": "HYDRA",
					"cardName": "HYDRA Kidnappers"
				},
				{
					"deckId": 119,
					"setId": 100,
					"cardImage": "sets/core/villains/hydra-02.jpg",
					"cardType": "Villain",
					"teamName": "HYDRA",
					"cardName": "Endless Armies Of HYDRA"
				},
				{
					"deckId": 119,
					"setId": 100,
					"cardImage": "sets/core/villains/hydra-03.jpg",
					"cardType": "Villain",
					"teamName": "HYDRA",
					"cardName": "Supreme HYDRA"
				},
				{
					"deckId": 119,
					"setId": 100,
					"cardImage": "sets/core/villains/hydra-04.jpg",
					"cardType": "Villain",
					"teamName": "HYDRA",
					"cardName": "Viper"
				}
			]
		},
		{
			"deckId": 120,
			"setId": 100,
			"deckImage": "sets/core/profilepics/brotherhood.jpg",
			"deckName": "Brotherhood",
			"deckType": "Villains",
			"cards": [
				{
					"deckId": 120,
					"setId": 100,
					"cardImage": "sets/core/villains/brotherhood-01.jpg",
					"cardType": "Villain",
					"teamName": "Brotherhood",
					"cardName": "Sabertooth"
				},
				{
					"deckId": 120,
					"setId": 100,
					"cardImage": "sets/core/villains/brotherhood-02.jpg",
					"cardType": "Villain",
					"teamName": "Brotherhood",
					"cardName": "Mystique"
				},
				{
					"deckId": 120,
					"setId": 100,
					"cardImage": "sets/core/villains/brotherhood-03.jpg",
					"cardType": "Villain",
					"teamName": "Brotherhood",
					"cardName": "Juggernaut"
				},
				{
					"deckId": 120,
					"setId": 100,
					"cardImage": "sets/core/villains/brotherhood-04.jpg",
					"cardType": "Villain",
					"teamName": "Brotherhood",
					"cardName": "Blob"
				}
			]
		},
		{
			"deckId": 121,
			"setId": 100,
			"deckImage": "sets/core/profilepics/masters-of-evil.jpg",
			"deckName": "Masters Of Evil",
			"deckType": "Villains",
			"cards": [
				{
					"deckId": 121,
					"setId": 100,
					"cardImage": "sets/core/villains/masters-of-evil-01.jpg",
					"cardType": "Villain",
					"teamName": "Masters Of Evil",
					"cardName": "Melter"
				},
				{
					"deckId": 121,
					"setId": 100,
					"cardImage": "sets/core/villains/masters-of-evil-02.jpg",
					"cardType": "Villain",
					"teamName": "Masters Of Evil",
					"cardName": "Baron Zemo"
				},
				{
					"deckId": 121,
					"setId": 100,
					"cardImage": "sets/core/villains/masters-of-evil-03.jpg",
					"cardType": "Villain",
					"teamName": "Masters Of Evil",
					"cardName": "Whirlwind"
				},
				{
					"deckId": 121,
					"setId": 100,
					"cardImage": "sets/core/villains/masters-of-evil-04.jpg",
					"cardType": "Villain",
					"teamName": "Masters Of Evil",
					"cardName": "Ultron"
				}
			]
		},
		{
			"deckId": 122,
			"setId": 100,
			"deckImage": "images/misc/henchmen.jpg",
			"deckName": "Henchmen",
			"deckType": "Henchmen",
			"cards": [
				{
					"deckId": 122,
					"setId": 100,
					"cardImage": "sets/core/henchmen/mandroid.jpg",
					"cardType": "Henchmen",
					"teamName": "Mandroid",
					"cardName": "Mandroid"
				},
				{
					"deckId": 122,
					"setId": 100,
					"cardImage": "sets/core/henchmen/doombot-legion.jpg",
					"cardType": "Henchmen",
					"teamName": "Doombot",
					"cardName": "Doombot Legion"
				},
				{
					"deckId": 122,
					"setId": 100,
					"cardImage": "sets/core/henchmen/sentinel.jpg",
					"cardType": "Henchmen",
					"teamName": "Sentinel",
					"cardName": "Sentinel"
				},
				{
					"deckId": 122,
					"setId": 100,
					"cardImage": "sets/core/henchmen/hand-ninjas.jpg",
					"cardType": "Villain",
					"teamName": "Hand Ninjas",
					"cardName": "Hand Ninjas"
				}
			]
		},
		{
			"deckId": 123,
			"setId": 100,
			"deckImage": "sets/core/other/scheme-twist.jpg",
			"deckName": "Schemes",
			"deckType": "Schemes",
			"cards": [
				{
					"deckId": 123,
					"setId": 100,
					"cardImage": "sets/core/schemes/scheme-01.jpg",
					"cardType": "Scheme",
					"teamName": "-",
					"cardName": "Super Civil War"
				},
				{
					"deckId": 123,
					"setId": 100,
					"cardImage": "sets/core/schemes/scheme-02.jpg",
					"cardType": "Scheme",
					"teamName": "-",
					"cardName": "Secret Invasion Of The Skrull Shapeshifters"
				},
				{
					"deckId": 123,
					"setId": 100,
					"cardImage": "sets/core/schemes/scheme-03.jpg",
					"cardType": "Scheme",
					"teamName": "-",
					"cardName": "Replace Eath's Leaders With Killbots"
				},
				{
					"deckId": 123,
					"setId": 100,
					"cardImage": "sets/core/schemes/scheme-04.jpg",
					"cardType": "Scheme",
					"teamName": "-",
					"cardName": "The Legacy Virus"
				},
				{
					"deckId": 123,
					"setId": 100,
					"cardImage": "sets/core/schemes/scheme-05.jpg",
					"cardType": "Scheme",
					"teamName": "-",
					"cardName": "Midtown Bank Robbery"
				},
				{
					"deckId": 123,
					"setId": 100,
					"cardImage": "sets/core/schemes/scheme-06.jpg",
					"cardType": "Scheme",
					"teamName": "-",
					"cardName": "Unleashe The Power Of The Cosmic Cube"
				},
				{
					"deckId": 123,
					"setId": 100,
					"cardImage": "sets/core/schemes/scheme-07.jpg",
					"cardType": "Scheme",
					"teamName": "-",
					"cardName": "Portals To The Dark Dimension"
				},
				{
					"deckId": 123,
					"setId": 100,
					"cardImage": "sets/core/schemes/scheme-08.jpg",
					"cardType": "Scheme",
					"teamName": "-",
					"cardName": "Negative Zone Prison Breakout"
				}
			]
		},
		{
			"deckId": 124,
			"setId": 100,
			"deckImage": "sets/core/other/shield-agent.jpg",
			"deckName": "General",
			"deckType": "General",
			"cards": [
				{
					"deckId": 124,
					"setId": 100,
					"cardImage": "sets/core/other/shield-agent.jpg",
					"cardType": "General",
					"teamName": "S.H.I.E.L.D.",
					"cardName": "S.H.I.E.L.D. Agent"
				},
				{
					"deckId": 124,
					"setId": 100,
					"cardImage": "sets/core/other/shield-trooper.jpg",
					"cardType": "General",
					"teamName": "S.H.I.E.L.D.",
					"cardName": "S.H.I.E.L.D. Trooper"
				},
				{
					"deckId": 124,
					"setId": 100,
					"cardImage": "sets/core/other/shield-officer.jpg",
					"cardType": "General",
					"teamName": "S.H.I.E.L.D.",
					"cardName": "S.H.I.E.L.D. Officer"
				},
				{
					"deckId": 124,
					"setId": 100,
					"cardImage": "sets/core/other/master-strike.jpg",
					"cardType": "General",
					"teamName": "-",
					"cardName": "Master Strike"
				},
				{
					"deckId": 124,
					"setId": 100,
					"cardImage": "sets/core/other/scheme-twist.jpg",
					"cardType": "General",
					"teamName": "-",
					"cardName": "Scheme Twist"
				},
				{
					"deckId": 124,
					"setId": 100,
					"cardImage": "sets/core/other/wound.jpg",
					"cardType": "General",
					"teamName": "-",
					"cardName": "Wound"
				},
				{
					"deckId": 124,
					"setId": 100,
					"cardImage": "sets/core/other/bystanders.jpg",
					"cardType": "General",
					"teamName": "-",
					"cardName": "Bystander"
				}
			]
		},
		{
			"deckId": 125,
			"setId": 100,
			"deckImage": "sets/core/villains/skrulls-01.jpg",
			"deckName": "Skrulls",
			"deckType": "Villains",
			"cards": [
				{
					"deckId": 125,
					"setId": 100,
					"cardImage": "sets/core/villains/skrulls-01.jpg",
					"cardType": "Villain",
					"teamName": "Skrulls",
					"cardName": "Paibok The Power Skrull"
				},
				{
					"deckId": 125,
					"setId": 100,
					"cardImage": "sets/core/villains/skrulls-02.jpg",
					"cardType": "Villain",
					"teamName": "Skrulls",
					"cardName": "Skrull Queen Veranke"
				},
				{
					"deckId": 125,
					"setId": 100,
					"cardImage": "sets/core/villains/skrulls-03.jpg",
					"cardType": "Villain",
					"teamName": "Skrulls",
					"cardName": "Skrull Shapeshifter"
				},
				{
					"deckId": 125,
					"setId": 100,
					"cardImage": "sets/core/villains/skrulls-04.jpg",
					"cardType": "Villain",
					"teamName": "Skrulls",
					"cardName": "Super-Skrull"
				}
			]
		}
	]
}